reloadify.py
reloadify-0.1.0.dist-info/licenses/LICENSE
reloadify-0.1.0.dist-info/METADATA
reloadify-0.1.0.dist-info/WHEEL
reloadify-0.1.0.dist-info/entry_points.txt
reloadify-0.1.0.dist-info/top_level.txt
reloadify-0.1.0.dist-info/RECORD
