Metadata-Version: 2.4
Name: reloadify
Version: 0.1.0
Summary: A blazing-fast, ultra-lightweight Python CLI tool for live-reloading web content.
Author-email: LousyBook01 <lousybook94@gmail.com>
Project-URL: Homepage, https://github.com/LousyBook94/reloadify
Project-URL: Bug Tracker, https://github.com/LousyBook94/reloadify/issues
Classifier: Programming Language :: Python :: 3
Classifier: License :: OSI Approved :: MIT License
Classifier: Operating System :: OS Independent
Requires-Python: >=3.7
License-File: LICENSE
Requires-Dist: click
Requires-Dist: rich
Requires-Dist: watchdog
Requires-Dist: websockets
Dynamic: license-file
